django_js_logger/__init__.py
django_js_logger/apps.py
django_js_logger/config.py
django_js_logger/static/django_js_logger/logger.js
django_js_logger/urls.py
django_js_logger/views.py
django_js_logger-1.0.0.dist-info/LICENSE
django_js_logger-1.0.0.dist-info/WHEEL
django_js_logger-1.0.0.dist-info/METADATA
django_js_logger-1.0.0.dist-info/RECORD
