Metadata-Version: 2.1
Name: django-js-logger
Version: 1.0.0
Summary: Frontend logging for Django projects
Home-page: https://github.com/snok/django-js-logger
License: BSD-4-Clause
Keywords: django
Author: Sondre Lillebø Gundersen
Author-email: sondrelg@live.no
Requires-Python: >=3.6.1,<4.0.0
Classifier: License :: Other/Proprietary License
Classifier: Programming Language :: Python :: 3
Classifier: Programming Language :: Python :: 3.7
Classifier: Programming Language :: Python :: 3.8
Requires-Dist: django (>=2.2,<4.0)
Requires-Dist: djangorestframework (>=3,<4)
